FastTrackML-0.6.0.data/data/bin/fml
FastTrackML-0.6.0.data/purelib/fasttrackml/__init__.py
FastTrackML-0.6.0.data/purelib/fasttrackml/client.py
FastTrackML-0.6.0.data/purelib/fasttrackml/fluent.py
FastTrackML-0.6.0.data/purelib/fasttrackml/_tracking_service/__init__.py
FastTrackML-0.6.0.data/purelib/fasttrackml/_tracking_service/client.py
FastTrackML-0.6.0.data/purelib/fasttrackml/entities/__init__.py
FastTrackML-0.6.0.data/purelib/fasttrackml/entities/metric.py
FastTrackML-0.6.0.data/purelib/fasttrackml/store/__init__.py
FastTrackML-0.6.0.data/purelib/fasttrackml/store/custom_rest_store.py
FastTrackML-0.6.0.dist-info/LICENSE
FastTrackML-0.6.0.dist-info/METADATA
FastTrackML-0.6.0.dist-info/WHEEL
FastTrackML-0.6.0.dist-info/top_level.txt
FastTrackML-0.6.0.dist-info/RECORD
