Metadata-Version: 2.1
Name: FastTrackML
Version: 0.6.0
Summary: An experiment tracking server focused on speed and scalability
License: Apache License
Project-URL: Homepage, https://fasttrackml.io/
Project-URL: Repository, https://github.com/G-Research/fasttrackml
Project-URL: Changelog, https://github.com/G-Research/fasttrackml/releases
Keywords: ai,apache-spark,data-science,data-visualization,experiment-tracking,machine-learning,metadata-tracking,metadata,metrics,ml,mlflow-tracking-server,mlflow,mlops,pytorch,tensorboard,tensorflow,visualization
Classifier: Development Status :: 4 - Beta
Classifier: Environment :: Web Environment
Classifier: Intended Audience :: Science/Research
Classifier: License :: OSI Approved :: Apache Software License
Classifier: Programming Language :: JavaScript
Classifier: Programming Language :: Python
Classifier: Programming Language :: Python :: 3
Classifier: Programming Language :: Python :: 3 :: Only
Classifier: Programming Language :: Python :: 3.9
Classifier: Programming Language :: Python :: 3.8
Classifier: Programming Language :: Python :: 3.7
Classifier: Programming Language :: Python :: 3.6
Classifier: Programming Language :: Python :: 3.11
Classifier: Programming Language :: Python :: 3.10
Classifier: Topic :: Scientific/Engineering
Classifier: Topic :: Utilities
Requires-Python: >=3.6
License-File: LICENSE
Requires-Dist: mlflow <3.0,>=2.8.0
